Mucklet/CachedDictionary.py
Mucklet/ResClient.py
Mucklet/__init__.py
Mucklet/bot.py
Mucklet/log.py
Mucklet/types.py
Mucklet-1.1.2.dist-info/LICENSE.md
Mucklet-1.1.2.dist-info/METADATA
Mucklet-1.1.2.dist-info/WHEEL
Mucklet-1.1.2.dist-info/top_level.txt
Mucklet-1.1.2.dist-info/RECORD
