Metadata-Version: 2.1
Name: Mucklet
Version: 1.1.2
Summary: A package for creating and using bots for the Mucklet role-playing service.
Home-page: https://github.com/IcoTwilight/PythonMuckletBot
Author: Ico Twilight
Author-email: Ico@duck.com
Project-URL: Bug Tracker, https://github.com/IcoTwilight/PythonMuckletBot/issues
Classifier: Programming Language :: Python :: 3
Classifier: License :: OSI Approved :: MIT License
Classifier: Operating System :: OS Independent
Requires-Python: >=3.6
License-File: LICENSE.md
Requires-Dist: websocket-client
Requires-Dist: bson
